AUTHORS
LICENSE
MANIFEST.in
README.rst
setup.py
django_jsonfield2.egg-info/PKG-INFO
django_jsonfield2.egg-info/SOURCES.txt
django_jsonfield2.egg-info/dependency_links.txt
django_jsonfield2.egg-info/requires.txt
django_jsonfield2.egg-info/top_level.txt
jsonfield2/__init__.py
jsonfield2/fields.py
jsonfield2/forms.py
jsonfield2/managers.py
jsonfield2/models.py
jsonfield2/utils.py
jsonfield2/widgets.py
jsonfield2/templatetags/__init__.py
jsonfield2/templatetags/jsonify.py
jsonfield2/tests/__init__.py
jsonfield2/tests/test_fields.py
jsonfield2/tests/test_forms.py
jsonfield2/tests/test_jsonquery.py
jsonfield2/tests/jsonfield_test_app/__init__.py
jsonfield2/tests/jsonfield_test_app/forms.py
jsonfield2/tests/jsonfield_test_app/models.py