Metadata-Version: 1.1
Name: django-jsonfield2
Version: 15.06.08
Summary: A flexible quering JSONField and associated form field to store validated JSON in your model.
Home-page: https://github.com/DarioGT/django-jsonfield2
Author: Dario Gomez-Tafur
Author-email: certae.sm@gmail.com
License: BSD
Platform: UNKNOWN
Classifier: Programming Language :: Python
Classifier: Programming Language :: Python :: 3.4
Classifier: License :: OSI Approved :: BSD License
Classifier: Operating System :: OS Independent
Classifier: Framework :: Django
Classifier: Development Status :: 3 - Alpha
Classifier: Intended Audience :: Developers
Classifier: Topic :: Software Development :: Libraries :: Python Modules
